numba/openmp/__init__.py
numba/openmp/_version.py
numba/openmp/analysis.py
numba/openmp/compiler.py
numba/openmp/config.py
numba/openmp/decorators.py
numba/openmp/exceptions.py
numba/openmp/ir_utils.py
numba/openmp/link_utils.py
numba/openmp/llvm_pass.py
numba/openmp/llvmlite_extensions.py
numba/openmp/omp_context.py
numba/openmp/omp_grammar.py
numba/openmp/omp_ir.py
numba/openmp/omp_lower.py
numba/openmp/omp_runtime.py
numba/openmp/overloads.py
numba/openmp/parser.py
numba/openmp/tags.py
numba/openmp/libs/libomp/lib/libgomp.so
numba/openmp/libs/libomp/lib/libiomp5.so
numba/openmp/libs/libomp/lib/libomp.so
numba/openmp/libs/libomp/lib/libomptarget-amdgpu-gfx1010.bc
numba/openmp/libs/libomp/lib/libomptarget-amdgpu-gfx1030.bc
numba/openmp/libs/libomp/lib/libomptarget-amdgpu-gfx1031.bc
numba/openmp/libs/libomp/lib/libomptarget-amdgpu-gfx1032.bc
numba/openmp/libs/libomp/lib/libomptarget-amdgpu-gfx1033.bc
numba/openmp/libs/libomp/lib/libomptarget-amdgpu-gfx1034.bc
numba/openmp/libs/libomp/lib/libomptarget-amdgpu-gfx1035.bc
numba/openmp/libs/libomp/lib/libomptarget-amdgpu-gfx1036.bc
numba/openmp/libs/libomp/lib/libomptarget-amdgpu-gfx700.bc
numba/openmp/libs/libomp/lib/libomptarget-amdgpu-gfx701.bc
numba/openmp/libs/libomp/lib/libomptarget-amdgpu-gfx801.bc
numba/openmp/libs/libomp/lib/libomptarget-amdgpu-gfx803.bc
numba/openmp/libs/libomp/lib/libomptarget-amdgpu-gfx900.bc
numba/openmp/libs/libomp/lib/libomptarget-amdgpu-gfx902.bc
numba/openmp/libs/libomp/lib/libomptarget-amdgpu-gfx906.bc
numba/openmp/libs/libomp/lib/libomptarget-amdgpu-gfx908.bc
numba/openmp/libs/libomp/lib/libomptarget-amdgpu-gfx90a.bc
numba/openmp/libs/libomp/lib/libomptarget-amdgpu-gfx90c.bc
numba/openmp/libs/libomp/lib/libomptarget-amdgpu-gfx940.bc
numba/openmp/libs/libomp/lib/libomptarget-nvptx-sm_35.bc
numba/openmp/libs/libomp/lib/libomptarget-nvptx-sm_37.bc
numba/openmp/libs/libomp/lib/libomptarget-nvptx-sm_50.bc
pyomp-0.4.0.dist-info/METADATA
pyomp-0.4.0.dist-info/WHEEL
pyomp-0.4.0.dist-info/top_level.txt
pyomp-0.4.0.dist-info/RECORD
pyomp-0.4.0.dist-info/licenses/LICENSE
pyomp-0.4.0.dist-info/licenses/LICENSE-OPENMP.txt
