Metadata-Version: 2.4
Name: pyomp
Version: 0.4.0
Summary: Python OpenMP library based on Numba
Maintainer-email: Giorgis Georgakoudis <georgakoudis1@llnl.gov>
License-Expression: BSD-2-Clause
Project-URL: Homepage, https://github.com/Python-for-HPC/PyOMP
Project-URL: Issues, https://github.com/Python-for-HPC/PyOMP/issues
Classifier: Programming Language :: Python :: 3
Classifier: Operating System :: OS Independent
Classifier: Development Status :: 4 - Beta
Classifier: Intended Audience :: Developers
Classifier: Topic :: Software Development :: Compilers
Requires-Python: <3.14,>=3.10
License-File: LICENSE
License-File: LICENSE-OPENMP.txt
Requires-Dist: numba<0.62,>=0.61
Requires-Dist: lark
Requires-Dist: cffi
Requires-Dist: setuptools
Dynamic: license-file
